pdf_bookmark_splitter/__init__.py
pdf_bookmark_splitter/cli.py
pdf_bookmark_splitter/main.py
pdf_bookmark_splitter/pdf_operations.py
pdf_bookmark_splitter-0.1.0.dist-info/METADATA
pdf_bookmark_splitter-0.1.0.dist-info/WHEEL
pdf_bookmark_splitter-0.1.0.dist-info/entry_points.txt
pdf_bookmark_splitter-0.1.0.dist-info/RECORD
