Metadata-Version: 2.4
Name: pdf-bookmark-splitter
Version: 0.1.0
Summary: A tool for splitting PDF files based on bookmarks
Project-URL: Homepage, https://github.com/leejss/pdf-bookmark-splitter
Author-email: leejss <goldemshine@gmail.com>
License: MIT
Classifier: License :: OSI Approved :: MIT License
Classifier: Operating System :: OS Independent
Classifier: Programming Language :: Python :: 3
Requires-Python: >=3.6
Requires-Dist: pypdf
